Workbook

Sheet DATA
A1: NO | B1: INV NO | C1: PI NO | D1: MODEL | E1: ORDER NO | F1: ITEM NO | G1: ENGINE NO | H1: VIN NO | I1: colour | J1: Engine Capacity | K1: CHASSIS NO | L1: CUSTOMER NAME | M1: SEATING | N1: U/P | O1: REG NO | P1: FINANCE COMPANY | Q1: INV DATE | R1: DELIVERY DATE | S1: COMPANY | T1: ADDRESS | U1: INVOICE ISSED BY | V1: CUSTOMER CONTRIBUTION | W1: LEASING
A2: 1 | C2: NCGH-YT-PI-2506001 | D2: ZK6907H (37+1+1) | E2: 454104 | F2: 25E371X-0025 | G2: A5CYAS30186 | H2: LZYTDTD68T1003362 | I2: GREEN | L2: Mr. Osanda | P2: N/A
A3: 2 | C3: NCGH-YT-PI-2506002 | D3: ZK6907H (37+1+1) | E3: 454107 | F3: 25E371X-0026 | G3: A5CYAS30181 | H3: LZYTDTD6XT1003363 | I3: WHITE | L3: Mr.Naveen Express | P3: N/A
A4: 3 | C4: NCGH-YT-PI-2506003 | D4: ZK6907H (37+1+1) | E4: 454109 | F4: 25E371X-0027 | G4: A5CYAS30188 | H4: LZYTDTD61T1003364 | I4: GREEN | L4: Mr.Thushara | P4: N/A
A5: 4 | C5: NCGH-YT-PI-2506004 | D5: ZK6907H (37+1+1) | E5: 454139 | F5: 25E371X-0043 | G5: A5CYAS30169 | H5: LZYTDTD6XT1003380 | I5: WHITE | L5: Mr. Duminda | P5: N/A
A6: 5 | C6: NCGH-YT-PI-2506005 | D6: ZK6907H (37+1+1) | E6: 454137 | F6: 25E371X-0039 | G6: A5CYAS30192 | H6: LZYTDTD68T1003376 | I6: WHITE | L6: Chandimal Upul | P6: N/A
A7: 6 | C7: NCGH-YT-PI-2506006 | D7: ZK6907H (37+1+1) | E7: 454137 | F7: 25E371X-0040 | G7: A5CYAS30180 | H7: LZYTDTD6XT1003377 | I7: WHITE | L7: A W Samarasekara | P7: N/A
A8: 7 | C8: NCGH-YT-PI-2506007 | D8: ZK6907H (37+1+1) | E8: 454137 | F8: 25E371X-0041 | G8: A5CYAS30179 | H8: LZYTDTD61T1003378 | I8: WHITE | L8: Mr. Lakmal | P8: N/A
A9: 8 | C9: NCGH-YT-PI-2506008 | D9: ZK6907H (37+1+1) | E9: 454137 | F9: 25E371X-0042 | G9: A5CYAS30185 | H9: LZYTDTD63T1003379 | I9: WHITE | L9: exstock | P9: N/A
A10: 9 | C10: NCGH-YT-PI-2506009 | D10: ZK6907H (35+1+1) | E10: 454134 | F10: 25E371X-0029 | G10: A5CYAS30182 | H10: LZYTDTD65T1003366 | I10: WHITE | L10: K A S Wimalarathna | P10: N/A
A11: 10 | C11: NCGH-YT-PI-2506010 | D11: ZK6907H (35+1+1) | E11: 454134 | F11: 25E371X-0030 | G11: A5CYAS30183 | H11: LZYTDTD67T1003367 | I11: WHITE | L11: Muthanthri / H A D Priyantha | P11: N/A
A12: 11 | C12: NCGH-YT-PI-2506011 | D12: ZK6907H (35+1+1) | E12: 454134 | F12: 25E371X-0031 | G12: A5CYAS30190 | H12: LZYTDTD69T1003368 | I12: WHITE | L12: Maduranga | P12: N/A
A13: 12 | C13: NCGH-YT-PI-2506012 | D13: ZK6907H (35+1+1) | E13: 454134 | F13: 25E371X-0032 | G13: A5CYAS30194 | H13: LZYTDTD60T1003369 | I13: WHITE | L13: KK SS Sandaruwan | P13: N/A
... A53: 52 | C53: NCGH-YT-PI-2506052 | D53: ZK6128H LUXURY | E53: 454897 | F53: 25B483X-0027 | G53: 7526A000122 | H53: LZYTATF67T1052154 | I53: NCG Paint | L53: NCG Express | P53: N/A

Sheet P INV 
B7: TO : | C7: =_xlfn.XLOOKUP(F8,DATA!C2:C53,DATA!P2:P53) -> N/A | F7: =_xlfn.XLOOKUP(F8,DATA!C2:C53,DATA!Q2:Q53) -> 0
E8: INVOICE NO | F8: NCGH-YT-PI-2506003
B9: CUSTOMER : | C9: =_xlfn.XLOOKUP(F8,DATA!C2:C53,DATA!L2:L53) -> Mr.Thushara
B10: COMPANY | C10: =_xlfn.XLOOKUP(F8,DATA!C2:C53,DATA!S2:S53) -> 0
B11: ADDRESS : | C11: =_xlfn.XLOOKUP(F8,DATA!C2:C53,DATA!T2:T53) -> 0
B13: DATE : | C13: =UPPER(TEXT(F7,"mmm ")&DAY(F7)&IF(AND(MOD(DAY(F7),100)>=11,MOD(DAY(F7),100)<=13),"TH",CHOOSE(MOD(DAY(F7),10)+1,"TH","ST","ND","RD","TH","TH","TH","TH","TH","TH"))&" "&TEXT(F7,"yyyy")) -> JAN 0TH 1900
B16: PRODUCT | D16: QTY | E16: UNIT PRICE | F16: TOTAL
B18: MAKE | C18: YUTONG | D18: 1 | E18: =_xlfn.XLOOKUP(F8,DATA!C2:C53,DATA!N2:N53) -> 0 | F18: =D18*E18 -> 0
B19: BUS MODEL | C19: =_xlfn.XLOOKUP(F8,DATA!C2:C53,DATA!D2:D53) -> ZK6907H (37+1+1)
B20: SEATING CAPACITY | C20: =_xlfn.XLOOKUP(F8,DATA!C2:C53,DATA!M2:M53) -> 0
B21: YEAR | C21: 2025
B22: CONDITION | C22: BRAND NEW
B23: COLOUR | C23: =_xlfn.TRANSLATE(_xlfn.XLOOKUP(F8,DATA!C2:C51,DATA!I2:I51)) -> GREEN
B24: ENGINE CAPACITY | C24: =_xlfn.XLOOKUP(F8,DATA!C2:C51,DATA!J2:J51) -> 0
B25: FUEL TYPE | C25: DIESEL
B26: ENGINE NO | C26: =_xlfn.XLOOKUP(F8,DATA!C2:C53,DATA!G2:G53) -> A5CYAS30188
B27: CHASIS NUMBER | C27: =_xlfn.XLOOKUP(F8,DATA!C2:C53,DATA!H2:H53) -> LZYTDTD61T1003364
B28: AMOUNT IN WORD (BALANCE PAYABLE) | C28: {=UPPER(SpellRupees(F30))} -> RUPEES | E28: SUB TOTAL | F28: =SUBTOTAL(9,F18) -> 0
E29: CUSTOMER CONTRIBUTION | F29: =F28-F30 -> 0
E30: Leasing Amount | F30: =_xlfn.XLOOKUP(F8,DATA!C2:C53,DATA!W2:W53) -> 0
B33: Payment Terms : Payment method - by Cheque or bank transfer
B35: ACCOUNT NAME | C35: NCG HOLDINGS (PRIVATE) LIMITED
B36: ACCOUNT NUMBER | C36: 2000511791
B37: BANK / BRANCH | C37: COMMERCIAL BANK - NUGEGODA

Sheet Final  INV
B7: TO : | C7: =_xlfn.XLOOKUP(F8,DATA!C2:C53,DATA!P2:P53) -> #N/A | F7: =_xlfn.XLOOKUP(F8,DATA!C2:C53,DATA!Q2:Q53) -> #N/A
E8: INVOICE NO | F8: NCGH-YT-PI-2505005
B9: CUSTOMER : | C9: =_xlfn.XLOOKUP(F8,DATA!C2:C53,DATA!L2:L53) -> #N/A
B10: COMPANY | C10: =_xlfn.XLOOKUP(F8,DATA!C2:C53,DATA!S2:S53) -> #N/A
B11: ADDRESS : | C11: =_xlfn.XLOOKUP(F8,DATA!C2:C53,DATA!T2:T53) -> #N/A
B13: DATE : | C13: =UPPER(TEXT(F7,"mmm ")&DAY(F7)&IF(AND(MOD(DAY(F7),100)>=11,MOD(DAY(F7),100)<=13),"TH",CHOOSE(MOD(DAY(F7),10)+1,"TH","ST","ND","RD","TH","TH","TH","TH","TH","TH"))&" "&TEXT(F7,"yyyy")) -> #N/A
B16: PRODUCT | D16: QTY | E16: UNIT PRICE | F16: TOTAL
B18: MAKE | C18: YUTONG | D18: 1 | E18: =_xlfn.XLOOKUP(F8,DATA!C2:C53,DATA!N2:N53) -> #N/A | F18: =D18*E18 -> #N/A
B19: BUS MODEL | C19: =_xlfn.XLOOKUP(F8,DATA!C2:C53,DATA!D2:D53) -> #N/A
B20: SEATING CAPACITY | C20: =_xlfn.XLOOKUP(F8,DATA!C2:C53,DATA!M2:M53) -> #N/A
B21: YEAR | C21: 2025
B22: CONDITION | C22: BRAND NEW
B23: COLOUR | C23: =_xlfn.TRANSLATE(_xlfn.XLOOKUP(F8,DATA!C2:C51,DATA!I2:I51)) -> #N/A
B24: ENGINE CAPACITY | C24: =_xlfn.XLOOKUP(F8,DATA!C2:C51,DATA!J2:J51) -> #N/A
B25: FUEL TYPE | C25: DIESEL
B26: ENGINE NO | C26: =_xlfn.XLOOKUP(F8,DATA!C2:C53,DATA!G2:G53) -> #N/A
B27: CHASIS NUMBER | C27: =_xlfn.XLOOKUP(F8,DATA!C2:C53,DATA!H2:H53) -> #N/A
B28: AMOUNT IN WORD (BALANCE PAYABLE) | C28: {=UPPER(SpellRupees(F30))} -> #VALUE! | E28: SELLING PRICE | F28: =SUBTOTAL(9,F18) -> #N/A
E29: CUSTOMER CONTRIBUTION | F29: =F28-F30 -> #N/A
E30: AMOUNT TO BE LEASED | F30: =_xlfn.XLOOKUP(F8,DATA!C2:C53,DATA!W2:W53) -> #N/A
B33: Payment Terms : Payment method - by Cheque or bank transfer
B35: ACCOUNT NAME | C35: NCG HOLDINGS (PRIVATE) LIMITED
B36: ACCOUNT NUMBER | C36: 2000511791
B37: BANK / BRANCH | C37: COMMERCIAL BANK - NUGEGODA

Sheet Final  INV (2)
F7: =_xlfn.XLOOKUP(F8,DATA!C2:C53,DATA!Q2:Q53) -> #N/A
E8: INVOICE NO | F8: NCGH-YT-PI-2505036
B9: CUSTOMER : | C9: =_xlfn.XLOOKUP(F8,DATA!C2:C53,DATA!L2:L53) -> #N/A
B11: ADDRESS : | C11: =_xlfn.XLOOKUP(F8,DATA!C2:C53,DATA!T2:T53) -> #N/A
B13: DATE : | C13: =UPPER(TEXT(F7,"mmm ")&DAY(F7)&IF(AND(MOD(DAY(F7),100)>=11,MOD(DAY(F7),100)<=13),"TH",CHOOSE(MOD(DAY(F7),10)+1,"TH","ST","ND","RD","TH","TH","TH","TH","TH","TH"))&" "&TEXT(F7,"yyyy")) -> #N/A
B16: PRODUCT | D16: QTY | E16: UNIT PRICE | F16: TOTAL
B18: MAKE | C18: YUTONG | D18: 1 | E18: =_xlfn.XLOOKUP(F8,DATA!C2:C53,DATA!N2:N53) -> #N/A | F18: =D18*E18 -> #N/A
B19: BUS MODEL | C19: =_xlfn.XLOOKUP(F8,DATA!C2:C53,DATA!D2:D53) -> #N/A
B20: SEATING CAPACITY | C20: =_xlfn.XLOOKUP(F8,DATA!C2:C53,DATA!M2:M53) -> #N/A
B21: YEAR | C21: 2025
B22: CONDITION | C22: BRAND NEW
B23: COLOUR | C23: =_xlfn.TRANSLATE(_xlfn.XLOOKUP(F8,DATA!C2:C51,DATA!I2:I51)) -> #N/A
B24: ENGINE CAPACITY | C24: =_xlfn.XLOOKUP(F8,DATA!C2:C51,DATA!J2:J51) -> #N/A
B25: FUEL TYPE | C25: DIESEL
B26: ENGINE NO | C26: =_xlfn.XLOOKUP(F8,DATA!C2:C53,DATA!G2:G53) -> #N/A
B27: CHASIS NUMBER | C27: =_xlfn.XLOOKUP(F8,DATA!C2:C53,DATA!H2:H53) -> #N/A
B28: AMOUNT IN WORD (BALANCE PAYABLE) | C28: {=UPPER(SpellRupees(F28))} -> #VALUE! | E28: SUB TOTAL | F28: =SUBTOTAL(9,F18) -> #N/A
E29: PAYMENT | F29: =F28-F30 -> #N/A
E30: TOTAL | F30: =_xlfn.XLOOKUP(F8,DATA!C2:C53,DATA!W2:W53) -> #N/A
B33: Payment Terms : Payment method - by Cheque or bank transfer
B35: ACCOUNT NAME | C35: NCG HOLDINGS (PRIVATE) LIMITED
B36: ACCOUNT NUMBER | C36: 2000511791
B37: BANK / BRANCH | C37: COMMERCIAL BANK - NUGEGODA
